{
  "metaTitle": "世界盡頭的意外相遇 住在冰雪之地的人們 | 專題 | 聯合報",
  "metaDescription": "氣候變遷、全球暖化為地球帶來嚴重影響，位在世界盡頭的格陵蘭首當其衝。冰山崩落、海冰快速消融，那些屬於極地的傳統文化、古蹟遺址也逐漸消逝。然而，在這座冰雪之島上，仍有一群人默默守護家園，他們對故鄉的熱愛，不會被冰雪結凍。",
  "metaKeywords": "格陵蘭,暖化,氣候變遷,全球暖化,格陵蘭人,自殺",
  "metaAuthor": "蕭衡倩、羅國俊、張正、蔡佩蓉、游昊耘、林雨荷、蘇韋豪、徐喬莉、楊若榆",
  "metaCopyright": "聯合報系",
  "metaUrl": "https://vip.udn.com/newmedia/2022/greenland/living/",
  "metaPublish": "2022-09-26 T00:00:00+08:00",
  "metaModified": "2022-09-26 T00:00:00+08:00",
  "editorInterviewTitle": "採訪團隊",
  "editorInterviewMembers": "梁玉芳、許詩愷、吳姿賢、陳靖宜、余承翰、游昌樺、李文顥",
  "editorProducerTitle": "製作人",
  "editorProducerMembers": "林雨荷、游昊耘、蔡佩蓉",
  "editorVisualTitle": "視覺設計",
  "editorVisualMembers": "徐喬莉、蘇韋豪",
  "editorEngineerTitle": "工程師",
  "editorEngineerMembers": "楊若榆",
  "editorDirectorTitle": "監製",
  "editorDirectorMembers": "蕭衡倩、羅國俊、張正",
  "editorGroupTitle": "製作單位",
  "editorGroupMembers": "聯合報新聞部、願景工程基金會",
  "editorReleaseDate": "2022.09.26",
  "introTitle": "世界盡頭的意外相遇",
  "introSubTitle": "住在冰雪之地的人們",
  "introText1": [
    "格陵蘭是隸屬丹麥、世界上面積最大的島嶼，全島80％被冰雪覆蓋，人口密度為0.028人每平方公里，全球排名倒數第二，僅次於南極洲。與排名全球第十、人口密度高達652人每平方公里的台灣相比，可說是地廣人稀。",
    "氣候變遷、全球暖化為地球帶來嚴重影響，位在世界盡頭的格陵蘭首當其衝，也讓這座遺世獨立的島嶼，浮現在眾人面前。除了冰山崩落、海冰快速消融之外，那些屬於極地的傳統文化、古蹟遺址也逐漸消逝。"
  ],
  "introText2": [
    "地處北極圈內的格陵蘭，一年四季有近一半的時間為永晝，另一半則為永夜，極端的晝夜時間、寒冷的環境，深深影響當地人的作息，住在格陵蘭患上心理疾病的風險比世上任何一個地方都高，維基百科甚至有一頁條目，大剌剌名為「格陵蘭自殺現象」。",
    "根據當地政府統計，每5個格陵蘭人之中，便有一人曾浮現自殺念頭，比例高居世界之最。而這裡的總人口不過5萬出頭。"
  ],
  "introText3": [
    "然而，面對惡劣的氣候與環境，在這座冰雪之島上，仍有一群人默默守護著家園，他們對故鄉的熱愛，不會被冰雪結凍。"
  ],
  "kirImg1Caption": "Kirstine Møller／35歲／努克國家博物館古蹟學者",
  "kirTitle": "<span>我們沒有錢，也沒有人，</span><span>或許只能眼睜睜看著它們消失吧？</span>",
  "kirText1": [
    "「在殖民者留下的房子裡，展示被殖民者的歷史，這不是很荒謬嗎？」，Kirstine帶我們走在格陵蘭國家博物館的木造房舍間，碎念了幾句，聲音極細，聽來卻十分堅定。",
    "這些展區過去曾是丹麥傳教士的宿舍、木作坊。就連裡頭的數千件展覽品，也是丹麥人兩世紀間從格陵蘭島掠奪的文物。直到70年代中期，雙方才協定物歸原主，當年這項計畫名為「Utimut」，格陵蘭語的意思是「回歸」。",
    "國家博物館位於格陵蘭首都努克最明媚的區域，一眼望去是湛藍海洋，五顏六色的木造房屋背風而建，窗外還能看到冰山漂浮，像極了明信片上的北歐渡假村；但當地人稱這裡「殖民者海灘」，因為1722年，第一名丹麥傳教士由此登陸。",
    "Kirstine身為丹麥後裔，卻選擇成為追尋因努特文化的研究者，「我必須了解過去300年，我的祖先如何控制這個國家，沒有人能代替我回答這個問題」。"
  ],
  "kirImg2Caption": "Kirstine（最上圖）是一位追尋因努特文化的研究者，她熱切地彎腰說明氣候變遷對古蹟的影響。",
  "kirText2": [
    "但消逝的速度總勝過守望。由於氣候變遷影響，海平面逐漸上升、冷熱交替更劇烈，連地下土層都鬆動了，導致古蹟結構嚴重損毀。全島6,000多處古蹟只有7人負責管理，「我們沒有錢，也沒有人，或許只能眼睜睜看著它們消失吧？」。",
    "話是這樣說，Kirstine的行為卻和這心情完全相反。熱情回覆我們的採訪邀約，還在暴風雨中帶領記者走進荒煙蔓草。她站在一個凹陷土堆裡，手舞足蹈說明：「這裡是古代因努特人的房舍」，狹長且向下傾斜的入口，既能阻擋寒風吹襲，也讓侵略者難以進門。",
    "海岸雜生的灰黃草叢，則是前人綁雪鞋、獵物時用的芒草遺下了種子，茁壯生長至今。Kirstine不斷彎腰解說、熱情激昂，盡力在有限時間內，讓我們看見這片土地的故事。",
    "回到10年前，當時的她尚未立下志業，甚至懷疑自己不適合。直到一位來自加拿大的因努特女性學者鼓勵Kirstine：「快去考博士班，妳一定可以！」。",
    "「我在這之前從來沒見過女性考古家，是她為我點亮這條路，我不想辜負她的期待」，如今，Kirstine在手腕刺上因努特圖騰，大方說出她的目標與擔憂，這是愛，也是她交付自己的責任，「我相信我做到了」。"
  ],
  "kajImg1Caption": "Kaj Henningser／45歲／船長",
  "kajTitle": "在我小時候，可以和朋友從岸邊一路走上冰山釣魚，現在冰川都後退了，只剩零星浮冰。",
  "kajText1": [
    "船頭前方滿是浮冰，左右包夾而來，散發凜冽寒氣和警訊。此刻船長Kaj Henningser熟練操控舵輪，盯著雷達確認經緯度，同時微調方向和船速，帶領我們離開這片極北狂洋，完全看不出他在幾年前還是位建築工。",
    "駕船在格陵蘭可謂全民技能。這座大島上的城鎮幾乎沒有公路連結，定居點散落在複雜峽灣中，不論想出門捕魚、打獵，甚至拜訪親友，都得依船出航。",
    "拜訪格陵蘭3週，我們搭遍各種船隻，從最小的無屋頂舢舨到厚重安全的破冰駁船，各有千秋。最常見的小遊艇叫做「Targa」，是芬蘭公司製造的經典型號。但北極圈太多人開著同一家造船廠生產的船隻，久而久之，他們便把類似尺寸的遊艇全稱為「Targa」了。",
    "Kaj神似法國影星尚雷諾，不只技術好，還懂得安撫全世界為冰山而來的好奇寶寶，硬漢五官的內心藏著一位幽默大師。",
    "當我們疑惑冰山為何透著各種顏色，藍白灰交雜？他操起濃濃口音的英文努力解釋，比手畫腳，最後甚至把船停下來，撐著扶手，彎腰從海中撿了塊小冰開起「浮冰小教室」，一定要你搞懂。",
    "原來在光線變化下，不同密度的冰層會折射出百變姿態。白色塊狀體代表它比較年輕，清澈透明的部份密度較高，裡頭的水分曾經融化，如今重新凍結成冰。遠方用肉眼無法看清的藍色區域，則是上頭積了水。",
    "至於有些灰黃的冰山呢？Kaj只用一個單字說明：「Dirty！」它們在結凍前先混進了沙土。"
  ],
  "kajImg2Caption": "Kaj是一位船長，他一邊帶領船上的乘客航向峽灣，一邊解釋造成冰山顏色不同的成因。",
  "kajText2": [
    "由於太多峽灣沒有碼頭，格陵蘭人的小船周遭都貼滿軟墊，方便船長直接把船頭「撞進」適合臨停的隙縫中，再讓乘客「跳上岸」。",
    "Kaj眼見有塊大小合宜的漂浮冰山，便使出這招格陵蘭船長密技。當眾人還摸不著頭緒，深怕成為下一艘鐵達尼號，他早已喬好角度，開朗呼喊我們爬過船頭，親腳踏上冰山拍照。",
    "接著眾人又一陣驚呼，不遠處有群大翅鯨正在翻騰，多達5隻鯨魚浮至海面換氣。當我們興奮拿起所有具備攝影功能的3C產品狂拍，詢問Kaj能不能再往前一點？Kaj先是搖搖頭，叮嚀著「隔壁有賞鯨團，我們不能靠太近」，下一秒又笑說：「但鯨魚自己往我們這裡游來了，這就是大自然的奧妙，哈哈哈！」。",
    "「在我小時候，可以和朋友從岸邊一路走上冰山釣魚，現在冰川都後退了，只剩零星浮冰」，但提及氣候變遷，Kaj露出了難得的嚴肅神情。",
    "40年來親眼看著冰層消逝，他以觀光船維生的同時，也不斷提醒乘客，「這是全球暖化的鐵證」，Kaj希望外國人離開格陵蘭後，莫忘這片美景何其脆弱。",
    "我們問，那現在的小朋友怎麼辦？船長話鋒一轉，臉上再度掛滿笑容：「那就開船啊！」，或許這份百餘年來荒野求生培養的積極性格，正是格陵蘭人迎戰氣候變遷的秘訣吧。"
  ],
  "pauImg1Caption": "Pauline Olsen／76歲／因努特兒歌創作者",
  "pauTitle": "<span>你看我們的長相，和你們一樣，</span><span>亞洲人是我們的表親！</span>",
  "pauText1": ["", "", "", ""],
  "pauImg2Caption": "",
  "pauText2": ["", "", "", ""],
  "pauImg3Caption": "",
  "pauText3": ["", "", "", ""],
  "chrisImg1Caption": "",
  "chrisTitle": "",
  "chrisText1": ["", "", "", ""],
  "chrisImg2Caption": "",
  "chrisText2": ["", "", "", ""],
  "aviImg1Caption": "",
  "aviTitle": ["", "", "", ""],
  "aviText1": ["", "", "", ""],
  "aviImg2Caption": "",
  "aviText2": ["", "", "", ""],
  "aviImg3Caption": "",
  "aviText3": ["", "", "", ""],
  "boImg1Caption": "",
  "boTitle": "",
  "boText1": ["", "", "", ""],
  "boImg2Caption": "",
  "boText2": ["", "", "", ""],
  "boImg3Caption": "",
  "boText3": ["", "", "", ""]
}
